Section-1/led_blink.v
module led_blink(
    input clk,    // clk stand for clock and is the oscillates between 0 and 1.
    output reg led // reg is a type that can hold a value, and is used in seq logic.
    );

reg [31:0]count; // 32  bit wide register.

always @(posedge clk) begin

if(count == 9) begin //Time is up
    count <= 0;             //Reset count register
    led <= ~led;            //Toggle led (in each second), with the bitwise not.
end else begin
    count <= count + 1;     //Counts 100MHz clock
    end

end

endmodule

Section-1/dump.vcd
$version Generated by VerilatedVcd $end
$timescale 1ps $end
 $scope module TOP $end
  $var wire 1 # clk $end
  $var wire 1 $ led $end
  $scope module led_blink $end
   $var wire 1 # clk $end
   $var wire 1 $ led $end
   $var wire 32 % count [31:0] $end
  $upscope $end
 $upscope $end
$enddefinitions $end


#0
1#
0$
b00000000000000000000000000000000 %
#2
b00000000000000000000000000000001 %
#4
b00000000000000000000000000000010 %
#6
b00000000000000000000000000000011 %
#8
b00000000000000000000000000000100 %
#10
b00000000000000000000000000000101 %
#12
b00000000000000000000000000000110 %
#14
b00000000000000000000000000000111 %
#16
b00000000000000000000000000001000 %
#18
b00000000000000000000000000001001 %
#20
1$
b00000000000000000000000000000000 %
#22
b00000000000000000000000000000001 %
#24
b00000000000000000000000000000010 %
#26
b00000000000000000000000000000011 %
#28
b00000000000000000000000000000100 %
#30
b00000000000000000000000000000101 %
#32
b00000000000000000000000000000110 %
#34
b00000000000000000000000000000111 %
#36
b00000000000000000000000000001000 %
#38
b00000000000000000000000000001001 %
#40
0$
b00000000000000000000000000000000 %
#42
b00000000000000000000000000000001 %
#44
b00000000000000000000000000000010 %
#46
b00000000000000000000000000000011 %
#48
b00000000000000000000000000000100 %
#50
b00000000000000000000000000000101 %
#52
b00000000000000000000000000000110 %
#54
b00000000000000000000000000000111 %
#56
b00000000000000000000000000001000 %
#58
b00000000000000000000000000001001 %
#60
1$
b00000000000000000000000000000000 %
#62
b00000000000000000000000000000001 %
#64
b00000000000000000000000000000010 %
#66
b00000000000000000000000000000011 %
#68
b00000000000000000000000000000100 %
#70
b00000000000000000000000000000101 %
#72
b00000000000000000000000000000110 %
#74
b00000000000000000000000000000111 %
#76
b00000000000000000000000000001000 %
#78
b00000000000000000000000000001001 %
#80
0$
b00000000000000000000000000000000 %
#82
b00000000000000000000000000000001 %
#84
b00000000000000000000000000000010 %
#86
b00000000000000000000000000000011 %
#88
b00000000000000000000000000000100 %
#90
b00000000000000000000000000000101 %
#92
b00000000000000000000000000000110 %
#94
b00000000000000000000000000000111 %
#96
b00000000000000000000000000001000 %
#98
b00000000000000000000000000001001 %
